siemens/__init__.py
siemens-0.1.0.dist-info/LICENSE
siemens-0.1.0.dist-info/WHEEL
siemens-0.1.0.dist-info/METADATA
siemens-0.1.0.dist-info/RECORD
